<annotation>
	<folder>bed</folder>
	<filename>bed (391).jpg</filename>
	<path>D:\Bangkit Program\Bangkit-CP\Bangkit-Final-Project-Dataset\img\train\bed\bed (391).jpg</path>
	<source>
		<database>Unknown</database>
	</source>
	<size>
		<width>300</width>
		<height>200</height>
		<depth>3</depth>
	</size>
	<segmented>0</segmented>
	<object>
		<name>bed</name>
		<pose>Unspecified</pose>
		<truncated>0</truncated>
		<difficult>0</difficult>
		<bndbox>
			<xmin>13</xmin>
			<ymin>15</ymin>
			<xmax>287</xmax>
			<ymax>180</ymax>
		</bndbox>
	</object>
</annotation>
