<annotation>
	<folder>table</folder>
	<filename>table (113).jpg</filename>
	<path>D:\Bangkit Program\Bangkit-CP\Bangkit-Final-Project-Dataset\img\train\table\table (113).jpg</path>
	<source>
		<database>Unknown</database>
	</source>
	<size>
		<width>551</width>
		<height>414</height>
		<depth>3</depth>
	</size>
	<segmented>0</segmented>
	<object>
		<name>table</name>
		<pose>Unspecified</pose>
		<truncated>0</truncated>
		<difficult>0</difficult>
		<bndbox>
			<xmin>19</xmin>
			<ymin>19</ymin>
			<xmax>534</xmax>
			<ymax>392</ymax>
		</bndbox>
	</object>
</annotation>
